README.rst
setup.py
musichaos/__init__.py
musichaos/__main__.py
musichaos/core.py
musichaos/errors.py
musichaos/helpers.py
musichaos.egg-info/PKG-INFO
musichaos.egg-info/SOURCES.txt
musichaos.egg-info/dependency_links.txt
musichaos.egg-info/entry_points.txt
musichaos.egg-info/requires.txt
musichaos.egg-info/top_level.txt