Metadata-Version: 1.1
Name: musichaos
Version: 0.0.1
Summary: tool to tidy up your music chaos
Home-page: https://github.com/timofurrer/musichaos
Author: Timo Furrer
Author-email: tuxtimo@gmail.com
License: MIT
Download-URL: https://github.com/timofurrer/musichaos
Platform: Linux
Platform: Windows
Platform: MAC OS X
Classifier: Development Status :: 4 - Beta
Classifier: Environment :: Console
Classifier: Intended Audience :: Developers
Classifier: Intended Audience :: Education
Classifier: Intended Audience :: Other Audience
Classifier: License :: OSI Approved :: MIT License
Classifier: Natural Language :: English
Classifier: Operating System :: MacOS :: MacOS X
Classifier: Operating System :: OS Independent
Classifier: Operating System :: Microsoft :: Windows
Classifier: Operating System :: Microsoft :: Windows :: Windows 7
Classifier: Operating System :: Microsoft :: Windows :: Windows XP
Classifier: Operating System :: POSIX
Classifier: Operating System :: POSIX :: Linux
Classifier: Programming Language :: Python
Classifier: Programming Language :: Python :: 2.7
Classifier: Programming Language :: Python :: 3
Classifier: Programming Language :: Python :: 3.3
Classifier: Programming Language :: Python :: 3.4
Classifier: Programming Language :: Python :: 3.5
Classifier: Programming Language :: Python :: Implementation
Classifier: Topic :: Education :: Testing
Classifier: Topic :: Software Development
Classifier: Topic :: Software Development :: Testing
